oblate/__init__.py
oblate/configs.py
oblate/contexts.py
oblate/exceptions.py
oblate/schema.py
oblate/type_validation.py
oblate/utils.py
oblate/validate.py
oblate/fields/__init__.py
oblate/fields/base.py
oblate/fields/nesting.py
oblate/fields/primitive.py
oblate/fields/structs.py
oblate/fields/typings.py
oblate-1.2.1.dist-info/LICENSE
oblate-1.2.1.dist-info/METADATA
oblate-1.2.1.dist-info/WHEEL
oblate-1.2.1.dist-info/top_level.txt
oblate-1.2.1.dist-info/RECORD
