Metadata-Version: 2.1
Name: oblate
Version: 1.2.1
Summary: Python library for data validation
Home-page: https://github.com/izxxr/oblate
Author: izxxr
License: MIT
Project-URL: Documentation, https://oblate.readthedocs.io
Project-URL: Issue tracker, https://github.com/izxxr/oblate/issues
Classifier: Development Status :: 2 - Pre-Alpha
Classifier: License :: OSI Approved :: MIT License
Classifier: Intended Audience :: Developers
Classifier: Natural Language :: English
Classifier: Operating System :: OS Independent
Classifier: Programming Language :: Python :: 3.7
Classifier: Programming Language :: Python :: 3.8
Classifier: Programming Language :: Python :: 3.9
Classifier: Programming Language :: Python :: 3.10
Classifier: Programming Language :: Python :: 3.11
Classifier: Programming Language :: Python :: 3.12
Classifier: Topic :: Internet
Classifier: Topic :: Software Development :: Libraries
Classifier: Topic :: Software Development :: Libraries :: Python Modules
Classifier: Topic :: Utilities
Classifier: Typing :: Typed
Requires-Python: >=3.7.0
License-File: LICENSE
Requires-Dist: typing-extensions (==4.*)
